{
    "Alt-Up": "MoveLinesUp",
    "Alt-Down": "MoveLinesDown",
    "Alt-Left": "WordLeft",
    "Alt-Right": "WordRight",

    "Alt-Shift-Left": "SelectWordLeft",
    "Alt-Shift-Right": "SelectWordRight",

    "Ctrl-Left": "StartOfLine",
    "Ctrl-Right": "EndOfLine",
    "Ctrl-Up": "CursorStart",
    "Ctrl-Down": "CursorEnd",

    "Ctrl-Shift-Left": "SelectToStartOfLine",
    "Ctrl-Shift-Right": "SelectToEndOfLine",
    "Ctrl-Shift-Up": "SelectToStart",
    "Ctrl-Shift-Down": "SelectToEnd",

    "Ctrl-a": "SelectAll",
    "Ctrl-b": "command:lsp goto-definition", // TODO: go to definition
    //"Ctrl-c": "Copy|CopyLine",
    "Ctrl-d": "DeleteLine",
    "Ctrl-f": "Find",
    "Ctrl-q": "Quit",
    "Ctrl-s": "Save",
    "Ctrl-v": "Paste",
    "Ctrl-x": "Cut|CopyLine&DeleteLine",

    "Alt-/": "lua:comment.comment",
    "CtrlUnderscore": "lua:comment.comment"
}
